qkcli.py
qkcli-0.0.1.dist-info/METADATA
qkcli-0.0.1.dist-info/WHEEL
qkcli-0.0.1.dist-info/top_level.txt
qkcli-0.0.1.dist-info/RECORD
